rcsb/__init__.py
rcsb/app/__init__.py
rcsb/app/chem/ElementSymbol.py
rcsb/app/chem/LogFilterUtils.py
rcsb/app/chem/ReloadDependencies.py
rcsb/app/chem/__init__.py
rcsb/app/chem/depictTools.py
rcsb/app/chem/descriptorMatch.py
rcsb/app/chem/formulaMatch.py
rcsb/app/chem/main.py
rcsb/app/chem/serverStatus.py
rcsb.app.chem-0.27.dist-info/LICENSE
rcsb.app.chem-0.27.dist-info/METADATA
rcsb.app.chem-0.27.dist-info/WHEEL
rcsb.app.chem-0.27.dist-info/entry_points.txt
rcsb.app.chem-0.27.dist-info/top_level.txt
rcsb.app.chem-0.27.dist-info/RECORD
