Metadata-Version: 2.1
Name: rcsb.app.chem
Version: 0.27
Summary: RCSB Chemical Search Service
Home-page: https://github.com/rcsb/py-rcsb_app_chem
Author: John Westbrook
Author-email: john.westbrook@rcsb.org
License: Apache 2.0
Platform: UNKNOWN
Classifier: Development Status :: 3 - Alpha
Classifier: Intended Audience :: Developers
Classifier: Natural Language :: English
Classifier: License :: OSI Approved :: Apache Software License
Classifier: Programming Language :: Python
Classifier: Programming Language :: Python :: 3
Classifier: Programming Language :: Python :: 3.8
Requires-Dist: fastapi[all] (==0.61.1)
Requires-Dist: pydantic (==1.6.1)
Requires-Dist: aiofiles (==0.5.0)
Requires-Dist: gunicorn (==20.0.4)
Requires-Dist: rcsb.utils.io (>=0.77)
Requires-Dist: rcsb.utils.chem (>=0.43)
Provides-Extra: dev
Requires-Dist: check-manifest ; extra == 'dev'
Provides-Extra: test
Requires-Dist: coverage ; extra == 'test'
